hy/__init__.py
hy/__main__.py
hy/_compat.py
hy/cmdline.py
hy/compiler.py
hy/completer.py
hy/errors.py
hy/importer.py
hy/macros.py
hy/model_patterns.py
hy/models.py
hy/version.py
hy/contrib/__init__.py
hy/contrib/botsbuildbots.hy
hy/contrib/hy_repr.hy
hy/contrib/loop.hy
hy/contrib/pprint.hy
hy/contrib/profile.hy
hy/contrib/sequences.hy
hy/contrib/walk.hy
hy/core/__init__.py
hy/core/bootstrap.hy
hy/core/language.hy
hy/core/macros.hy
hy/core/shadow.hy
hy/extra/__init__.py
hy/extra/anaphoric.hy
hy/extra/reserved.hy
hy/lex/__init__.py
hy/lex/exceptions.py
hy/lex/lexer.py
hy/lex/parser.py
hy-0.20.0.data/data/get_version/get_version.py
hy-0.20.0.dist-info/AUTHORS
hy-0.20.0.dist-info/LICENSE
hy-0.20.0.dist-info/METADATA
hy-0.20.0.dist-info/WHEEL
hy-0.20.0.dist-info/entry_points.txt
hy-0.20.0.dist-info/top_level.txt
hy-0.20.0.dist-info/RECORD
